{
  "date": "2024-02-04",
  "count": 1,
  "papers": [
    {
      "id": "arxiv-2402-02500",
      "source": "conf",
      "title": "Point Cloud Matters: Rethinking the Impact of Different Observation Spaces on Robot Learning",
      "title_zh": "点云至关重要：重新思考不同观测空间对机器人学习的影响",
      "tldr_zh": "点云观测在机器人学习中优于RGB和RGB-D，尤其在泛化能力上表现突出。",
      "cover_zh": "点云才是王道？简单方法竟碾压RGB，机器人学习新发现！",
      "abstract_zh": "在机器人学习中，观测空间至关重要，因为不同模态具有独特的特性，可能成为除策略设计之外的瓶颈。在本研究中，我们探讨了不同观测空间对机器人学习的影响，重点关注三种主要模态：RGB、RGB-D和点云。我们引入了OBSBench，一个包含两个模拟器和125个任务的基准，以及针对各种编码器和策略基线的标准化流程。在多种接触丰富的操作任务上的大量实验揭示了一个显著趋势：基于点云的方法，即使是最简单的设计，也常常优于RGB和RGB-D方法。这一趋势在从头训练和利用预训练两种场景中均持续存在。此外，我们的发现表明，点云观测通常能带来更好的策略性能和显著更强的泛化能力，跨越各种几何和视觉条件。这些结果表明，3D点云是复杂机器人任务中一种有价值的观测模态。我们还建议，结合外观和坐标信息可以提升点云方法的性能。我们希望我们的工作能为设计更通用、更鲁棒的机器人模型提供有价值的见解和指导。代码可在https://github.com/HaoyiZhu/PointCloudMatters获取。",
      "authors": [
        "Haoyi Zhu",
        "Yating Wang",
        "Di Huang"
      ],
      "authors_all": [
        "Haoyi Zhu",
        "Yating Wang",
        "Di Huang",
        "Weicai Ye",
        "Wanli Ouyang",
        "Tong He"
      ],
      "primary_category": "",
      "published": "2024-02-04",
      "channels": [
        "manipulation"
      ],
      "badges": [
        {
          "kind": "venue",
          "label": "🎓 NeurIPS 2024"
        }
      ],
      "cover_image": "",
      "preview_pages": [],
      "arxiv_id": "2402.02500",
      "abs_url": "https://arxiv.org/abs/2402.02500",
      "pdf_url": "https://arxiv.org/pdf/2402.02500",
      "venue": "NeurIPS 2024",
      "venue_announced": "",
      "score": 24,
      "judge": {},
      "institutions": [],
      "method_tags": [],
      "platform": [],
      "sim_stack": [],
      "method_family": "",
      "real_robot": "",
      "training_summary": "",
      "demo_videos": [],
      "github": {},
      "source_tags": []
    }
  ]
}