{
  "date": "2024-08-13",
  "count": 1,
  "papers": [
    {
      "id": "arxiv-2408-07147",
      "source": "conf",
      "title": "Controlling the World by Sleight of Hand",
      "title_zh": "Controlling the World by Sleight of Hand",
      "tldr_zh": "",
      "cover_zh": "",
      "abstract_zh": "",
      "authors": [
        "Sruthi Sudhakar",
        "Ruoshi Liu",
        "Basile Van Hoorick"
      ],
      "authors_all": [
        "Sruthi Sudhakar",
        "Ruoshi Liu",
        "Basile Van Hoorick",
        "Carl Vondrick",
        "Richard S. Zemel"
      ],
      "primary_category": "",
      "published": "2024-08-13",
      "channels": [
        "manipulation",
        "world-model"
      ],
      "badges": [
        {
          "kind": "venue",
          "label": "🎓 ECCV 2024"
        }
      ],
      "cover_image": "",
      "preview_pages": [],
      "arxiv_id": "2408.07147",
      "abs_url": "https://arxiv.org/abs/2408.07147",
      "pdf_url": "https://arxiv.org/pdf/2408.07147",
      "venue": "ECCV 2024",
      "venue_announced": "",
      "score": 27,
      "judge": {},
      "institutions": [],
      "method_tags": [],
      "platform": [],
      "sim_stack": [],
      "method_family": "",
      "real_robot": "",
      "training_summary": "",
      "demo_videos": [],
      "github": {},
      "source_tags": []
    }
  ]
}