{
  "date": "2024-07-16",
  "count": 1,
  "papers": [
    {
      "id": "arxiv-2407-11954",
      "source": "conf",
      "title": "Gated Temporal Diffusion for Stochastic Long-Term Dense Anticipation",
      "title_zh": "Gated Temporal Diffusion for Stochastic Long-Term Dense Anticipation",
      "tldr_zh": "",
      "cover_zh": "",
      "abstract_zh": "",
      "authors": [
        "Olga Zatsarynna",
        "E. Bahrami",
        "Yazan Abu Farha"
      ],
      "authors_all": [
        "Olga Zatsarynna",
        "E. Bahrami",
        "Yazan Abu Farha",
        "Gianpiero Francesca",
        "Juergen Gall"
      ],
      "primary_category": "",
      "published": "2024-07-16",
      "channels": [
        "manipulation"
      ],
      "badges": [
        {
          "kind": "venue",
          "label": "🎓 ECCV 2024"
        }
      ],
      "cover_image": "",
      "preview_pages": [],
      "arxiv_id": "2407.11954",
      "abs_url": "https://arxiv.org/abs/2407.11954",
      "pdf_url": "https://arxiv.org/pdf/2407.11954",
      "venue": "ECCV 2024",
      "venue_announced": "",
      "score": 21,
      "judge": {},
      "institutions": [],
      "method_tags": [],
      "platform": [],
      "sim_stack": [],
      "method_family": "",
      "real_robot": "",
      "training_summary": "",
      "demo_videos": [],
      "github": {},
      "source_tags": []
    }
  ]
}