{
  "date": "2025-07-15",
  "count": 1,
  "papers": [
    {
      "id": "arxiv-2507-11296",
      "source": "conf",
      "title": "Diffusion-Based Imaginative Coordination for Bimanual Manipulation",
      "title_zh": "基于扩散的想象协调用于双臂操作",
      "tldr_zh": "提出扩散框架联合优化视频与动作预测，提升双臂操作成功率。",
      "cover_zh": "机器人双臂操作太难？这个扩散框架让成功率飙升32.5%！",
      "abstract_zh": "双臂操作在机器人领域至关重要，能够实现工业自动化和家庭服务中的复杂任务。然而，由于高维动作空间和复杂的协调要求，它带来了重大挑战。虽然视频预测最近被研究用于表示学习和控制，利用其捕捉丰富动态和行为信息的能力，但其增强双臂协调的潜力仍未得到充分探索。为了弥补这一差距，我们提出了一个统一的基于扩散的框架，用于视频和动作预测的联合优化。具体来说，我们提出了一种多帧潜在预测策略，在压缩的潜在空间中编码未来状态，保留任务相关特征。此外，我们引入了一种单向注意力机制，其中视频预测以动作为条件，而动作预测独立于视频预测。这种设计允许我们在推理时省略视频预测，显著提高效率。在两个模拟基准和一个真实世界环境中的实验表明，与强基线ACT相比，我们的方法在成功率上取得了显著提升，在ALOHA上提高了24.9%，在RoboTwin上提高了11.1%，在真实世界实验中提高了32.5%。我们的模型和代码在Diffusion_based_imaginative_Coordination公开。",
      "authors": [
        "Huilin Xu",
        "Jian Ding",
        "Jiakun Xu"
      ],
      "authors_all": [
        "Huilin Xu",
        "Jian Ding",
        "Jiakun Xu",
        "Ruixiang Wang",
        "Jun Chen",
        "Jinjie Mai",
        "Yanwei Fu",
        "Bernard Ghanem",
        "Feng Xu",
        "Mohamed Elhoseiny"
      ],
      "primary_category": "",
      "published": "2025-07-15",
      "channels": [
        "manipulation"
      ],
      "badges": [
        {
          "kind": "venue",
          "label": "🎓 ICCV 2025"
        }
      ],
      "cover_image": "",
      "preview_pages": [],
      "arxiv_id": "2507.11296",
      "abs_url": "https://arxiv.org/abs/2507.11296",
      "pdf_url": "https://arxiv.org/pdf/2507.11296",
      "venue": "ICCV 2025",
      "venue_announced": "",
      "score": 22,
      "judge": {},
      "institutions": [],
      "method_tags": [],
      "platform": [],
      "sim_stack": [],
      "method_family": "",
      "real_robot": "",
      "training_summary": "",
      "demo_videos": [],
      "github": {},
      "source_tags": []
    }
  ]
}