{
  "date": "2025-01-07",
  "count": 1,
  "papers": [
    {
      "id": "arxiv-2501-03575",
      "source": "manual_arxiv",
      "title": "Cosmos World Foundation Model Platform for Physical AI",
      "title_zh": "Cosmos 世界基础模型平台：面向物理 AI",
      "tldr_zh": "提出 Cosmos 平台，通过开源世界基础模型助力物理 AI 数字化训练。",
      "cover_zh": "物理AI先要数字训练？这个开源世界模型平台让定制像搭积木",
      "abstract_zh": "物理 AI 需要先进行数字化训练。它需要自身的数字孪生（策略模型）以及世界的数字孪生（世界模型）。本文提出 Cosmos 世界基础模型平台，帮助开发者为其物理 AI 系统构建定制化的世界模型。我们将世界基础模型定位为通用世界模型，可通过微调适配下游应用。该平台涵盖视频处理管线、预训练的世界基础模型、后训练示例以及视频分词器。为助力物理 AI 开发者解决社会关键问题，我们开源了 Cosmos，并以宽松许可协议开放模型权重，详见 https://github.com/nvidia-cosmos/cosmos-predict1。",
      "authors": [
        "NVIDIA",
        ":",
        "Niket Agarwal"
      ],
      "authors_all": [
        "NVIDIA",
        ":",
        "Niket Agarwal",
        "Arslan Ali",
        "Maciej Bala",
        "Yogesh Balaji",
        "Erik Barker",
        "Tiffany Cai",
        "Prithvijit Chattopadhyay",
        "Yongxin Chen",
        "Yin Cui",
        "Yifan Ding",
        "Daniel Dworakowski",
        "Jiaojiao Fan",
        "Michele Fenzi",
        "Francesco Ferroni",
        "Sanja Fidler",
        "Dieter Fox",
        "Songwei Ge",
        "Yunhao Ge",
        "Jinwei Gu",
        "Siddharth Gururani",
        "Ethan He",
        "Jiahui Huang",
        "Jacob Huffman",
        "Pooya Jannaty",
        "Jingyi Jin",
        "Seung Wook Kim",
        "Gergely Klár",
        "Grace Lam",
        "Shiyi Lan",
        "Laura Leal-Taixe",
        "Anqi Li",
        "Zhaoshuo Li",
        "Chen-Hsuan Lin",
        "Tsung-Yi Lin",
        "Huan Ling",
        "Ming-Yu Liu",
        "Xian Liu",
        "Alice Luo",
        "Qianli Ma",
        "Hanzi Mao",
        "Kaichun Mo",
        "Arsalan Mousavian",
        "Seungjun Nah",
        "Sriharsha Niverty",
        "David Page",
        "Despoina Paschalidou",
        "Zeeshan Patel",
        "Lindsey Pavao",
        "Morteza Ramezanali",
        "Fitsum Reda",
        "Xiaowei Ren",
        "Vasanth Rao Naik Sabavat",
        "Ed Schmerling",
        "Stella Shi",
        "Bartosz Stefaniak",
        "Shitao Tang",
        "Lyne Tchapmi",
        "Przemek Tredak",
        "Wei-Cheng Tseng",
        "Jibin Varghese",
        "Hao Wang",
        "Haoxiang Wang",
        "Heng Wang",
        "Ting-Chun Wang",
        "Fangyin Wei",
        "Xinyue Wei",
        "Jay Zhangjie Wu",
        "Jiashu Xu",
        "Wei Yang",
        "Lin Yen-Chen",
        "Xiaohui Zeng",
        "Yu Zeng",
        "Jing Zhang",
        "Qinsheng Zhang",
        "Yuxuan Zhang",
        "Qingqing Zhao",
        "Artur Zolkowski"
      ],
      "primary_category": "cs.CV",
      "published": "2025-01-07",
      "channels": [
        "world-model"
      ],
      "badges": [
        {
          "kind": "lab",
          "label": "⭐ NVIDIA"
        },
        {
          "kind": "pin",
          "label": "📌 站长精选"
        }
      ],
      "cover_image": "assets/img/covers/arxiv-2501-03575.jpg",
      "preview_pages": [
        "assets/img/covers/arxiv-2501-03575-p2.jpg",
        "assets/img/covers/arxiv-2501-03575-p3.jpg",
        "assets/img/covers/arxiv-2501-03575-p4.jpg"
      ],
      "arxiv_id": "2501.03575",
      "abs_url": "http://arxiv.org/abs/2501.03575v3",
      "pdf_url": "https://arxiv.org/pdf/2501.03575v3",
      "venue": "",
      "venue_announced": "",
      "score": 78,
      "judge": {},
      "institutions": [
        "NVIDIA"
      ],
      "method_tags": [
        "World Foundation Model",
        "pre-training and post-training"
      ],
      "platform": [],
      "sim_stack": [],
      "method_family": "",
      "real_robot": "",
      "training_summary": "",
      "demo_videos": [],
      "github": {}
    }
  ]
}