{
  "date": "2025-07-17",
  "count": 1,
  "papers": [
    {
      "id": "arxiv-2507-13019",
      "source": "conf",
      "title": "Rethinking the Embodied Gap in Vision-and-Language Navigation: A Holistic Study of Physical and Visual Disparities",
      "title_zh": "Rethinking the Embodied Gap in Vision-and-Language Navigation: A Holistic Study of Physical and Visual Disparities",
      "tldr_zh": "",
      "cover_zh": "",
      "abstract_zh": "",
      "authors": [
        "Liuyi Wang",
        "Xinyuan Xia",
        "Hui Zhao"
      ],
      "authors_all": [
        "Liuyi Wang",
        "Xinyuan Xia",
        "Hui Zhao",
        "Hanqing Wang",
        "Tai Wang",
        "Yilun Chen",
        "Chengju Liu",
        "Qijun Chen",
        "Jiangmiao Pang"
      ],
      "primary_category": "",
      "published": "2025-07-17",
      "channels": [
        "locomotion"
      ],
      "badges": [
        {
          "kind": "lab",
          "label": "⭐ Jiangmiao Pang"
        },
        {
          "kind": "venue",
          "label": "🎓 ICCV 2025"
        }
      ],
      "cover_image": "",
      "preview_pages": [],
      "arxiv_id": "2507.13019",
      "abs_url": "https://arxiv.org/abs/2507.13019",
      "pdf_url": "https://arxiv.org/pdf/2507.13019",
      "venue": "ICCV 2025",
      "venue_announced": "",
      "score": 39,
      "judge": {},
      "institutions": [],
      "method_tags": [],
      "platform": [],
      "sim_stack": [],
      "method_family": "",
      "real_robot": "",
      "training_summary": "",
      "demo_videos": [],
      "github": {},
      "source_tags": []
    }
  ]
}