{
  "date": "2025-03-02",
  "count": 2,
  "papers": [
    {
      "id": "arxiv-2503-00986",
      "source": "conf",
      "title": "Modeling Fine-Grained Hand-Object Dynamics for Egocentric Video Representation Learning",
      "title_zh": "Modeling Fine-Grained Hand-Object Dynamics for Egocentric Video Representation Learning",
      "tldr_zh": "",
      "cover_zh": "",
      "abstract_zh": "",
      "authors": [
        "Baoqi Pei",
        "Yifei Huang",
        "Jilan Xu"
      ],
      "authors_all": [
        "Baoqi Pei",
        "Yifei Huang",
        "Jilan Xu",
        "Guo Chen",
        "Yuping He",
        "Lijin Yang",
        "Yali Wang",
        "Weidi Xie",
        "Yu Qiao",
        "Fei Wu",
        "Limin Wang"
      ],
      "primary_category": "",
      "published": "2025-03-02",
      "channels": [
        "manipulation"
      ],
      "badges": [
        {
          "kind": "venue",
          "label": "🎓 ICLR 2025"
        }
      ],
      "cover_image": "",
      "preview_pages": [],
      "arxiv_id": "2503.00986",
      "abs_url": "https://arxiv.org/abs/2503.00986",
      "pdf_url": "https://arxiv.org/pdf/2503.00986",
      "venue": "ICLR 2025",
      "venue_announced": "",
      "score": 21,
      "judge": {},
      "institutions": [],
      "method_tags": [],
      "platform": [],
      "sim_stack": [],
      "method_family": "",
      "real_robot": "",
      "training_summary": "",
      "demo_videos": [],
      "github": {},
      "source_tags": []
    },
    {
      "id": "arxiv-2503-00870",
      "source": "conf",
      "title": "NeSyC: A Neuro-symbolic Continual Learner For Complex Embodied Tasks In Open Domains",
      "title_zh": "NeSyC: A Neuro-symbolic Continual Learner For Complex Embodied Tasks In Open Domains",
      "tldr_zh": "",
      "cover_zh": "",
      "abstract_zh": "",
      "authors": [
        "Wonje Choi",
        "Jinwoo Park",
        "Sanghyun Ahn"
      ],
      "authors_all": [
        "Wonje Choi",
        "Jinwoo Park",
        "Sanghyun Ahn",
        "Daehee Lee",
        "Honguk Woo"
      ],
      "primary_category": "",
      "published": "2025-03-02",
      "channels": [
        "manipulation"
      ],
      "badges": [
        {
          "kind": "venue",
          "label": "🎓 ICLR 2025"
        }
      ],
      "cover_image": "",
      "preview_pages": [],
      "arxiv_id": "2503.00870",
      "abs_url": "https://arxiv.org/abs/2503.00870",
      "pdf_url": "https://arxiv.org/pdf/2503.00870",
      "venue": "ICLR 2025",
      "venue_announced": "",
      "score": 13,
      "judge": {},
      "institutions": [],
      "method_tags": [],
      "platform": [],
      "sim_stack": [],
      "method_family": "",
      "real_robot": "",
      "training_summary": "",
      "demo_videos": [],
      "github": {},
      "source_tags": []
    }
  ]
}