{
  "date": "2025-05-06",
  "count": 1,
  "papers": [
    {
      "id": "arxiv-2505-03172",
      "source": "conf",
      "title": "Null Counterfactual Factor Interactions for Goal-Conditioned Reinforcement Learning",
      "title_zh": "Null Counterfactual Factor Interactions for Goal-Conditioned Reinforcement Learning",
      "tldr_zh": "",
      "cover_zh": "",
      "abstract_zh": "",
      "authors": [
        "Caleb Chuck",
        "Fan Feng",
        "Carl Qi"
      ],
      "authors_all": [
        "Caleb Chuck",
        "Fan Feng",
        "Carl Qi",
        "Chang Shi",
        "Siddhant Agarwal",
        "Amy Zhang",
        "S. Niekum"
      ],
      "primary_category": "",
      "published": "2025-05-06",
      "channels": [
        "locomotion"
      ],
      "badges": [
        {
          "kind": "venue",
          "label": "🎓 ICLR 2025"
        }
      ],
      "cover_image": "",
      "preview_pages": [],
      "arxiv_id": "2505.03172",
      "abs_url": "https://arxiv.org/abs/2505.03172",
      "pdf_url": "https://arxiv.org/pdf/2505.03172",
      "venue": "ICLR 2025",
      "venue_announced": "",
      "score": 13,
      "judge": {},
      "institutions": [],
      "method_tags": [],
      "platform": [],
      "sim_stack": [],
      "method_family": "",
      "real_robot": "",
      "training_summary": "",
      "demo_videos": [],
      "github": {},
      "source_tags": []
    }
  ]
}