{
  "date": "2026-05-05",
  "count": 1,
  "papers": [
    {
      "id": "vid-youtube-UoHfGhLHRkg",
      "source": "video_youtube",
      "title": "Atlas' Balancing Act | Boston Dynamics",
      "title_zh": "Atlas 的平衡术 | 波士顿动力",
      "tldr_zh": "波士顿动力通过Atlas平衡商业与科研。",
      "cover_zh": "机器人界的平衡大师｜波士顿动力如何让Atlas兼顾商业与科研？",
      "abstract_zh": "平衡商业目标与机器人研究可能很棘手，但通过 Atlas，我们正在让它成为现实。",
      "authors": [],
      "primary_category": "video",
      "published": "2026-05-05",
      "channels": [
        "loco-manip-wbc"
      ],
      "badges": [],
      "cover_image": "",
      "preview_pages": [],
      "arxiv_id": "",
      "abs_url": "https://www.youtube.com/shorts/UoHfGhLHRkg",
      "pdf_url": "",
      "score": 18,
      "judge": {},
      "institutions": [
        "Boston Dynamics"
      ],
      "method_tags": [],
      "platform": [],
      "sim_stack": [],
      "method_family": "",
      "real_robot": "",
      "training_summary": "",
      "demo_videos": [
        {
          "kind": "youtube",
          "url": "https://www.youtube.com/shorts/UoHfGhLHRkg",
          "embed_url": "https://www.youtube.com/embed/UoHfGhLHRkg",
          "title": "Atlas' Balancing Act | Boston Dynamics",
          "source": "channel"
        }
      ]
    }
  ]
}