{
  "id": "arxiv-2408-14472",
  "source": "manual_arxiv",
  "title": "Advancing Humanoid Locomotion: Mastering Challenging Terrains with Denoising World Model Learning",
  "title_zh": "推进人形机器人运动：通过去噪世界模型学习掌握挑战性地形",
  "abstract": "Humanoid robots, with their human-like skeletal structure, are especially suited for tasks in human-centric environments. However, this structure is accompanied by additional challenges in locomotion controller design, especially in complex real-world environments. As a result, existing humanoid robots are limited to relatively simple terrains, either with model-based control or model-free reinforcement learning. In this work, we introduce Denoising World Model Learning (DWL), an end-to-end reinforcement learning framework for humanoid locomotion control, which demonstrates the world's first humanoid robot to master real-world challenging terrains such as snowy and inclined land in the wild, up and down stairs, and extremely uneven terrains. All scenarios run the same learned neural network with zero-shot sim-to-real transfer, indicating the superior robustness and generalization capability of the proposed method.",
  "abstract_zh": "人形机器人因其类人骨骼结构，特别适合在人类为中心的环境中执行任务。然而，这种结构也给运动控制器设计带来了额外挑战，尤其是在复杂的现实环境中。因此，现有的人形机器人仅限于相对简单的地形，无论是基于模型的控制还是无模型的强化学习。在这项工作中，我们引入了去噪世界模型学习（DWL），一种用于人形机器人运动控制的端到端强化学习框架，它展示了世界上首个能够在真实挑战性地形上运动的人形机器人，例如野外雪地和倾斜地面、上下楼梯以及极度不平坦的地形。所有场景均使用相同的学习神经网络，实现零样本的仿真到现实迁移，表明所提方法具有卓越的鲁棒性和泛化能力。",
  "tldr_zh": "提出去噪世界模型学习，实现人形机器人在雪地、楼梯等复杂地形零样本迁移。",
  "cover_zh": "人形机器人首次征服雪地楼梯｜去噪世界模型让零样本迁移成为现实",
  "authors": [
    {
      "name": "Xinyang Gu",
      "affiliation": ""
    },
    {
      "name": "Yen-Jen Wang",
      "affiliation": ""
    },
    {
      "name": "Xiang Zhu",
      "affiliation": ""
    },
    {
      "name": "Chengming Shi",
      "affiliation": ""
    },
    {
      "name": "Yanjiang Guo",
      "affiliation": ""
    },
    {
      "name": "Yichen Liu",
      "affiliation": ""
    },
    {
      "name": "Jianyu Chen",
      "affiliation": ""
    }
  ],
  "primary_category": "cs.RO",
  "categories": [
    "cs.RO",
    "cs.AI",
    "eess.SY"
  ],
  "published": "2024-08-26",
  "updated": "2024-08-26",
  "arxiv_id": "2408.14472",
  "pdf_url": "https://arxiv.org/pdf/2408.14472v1",
  "abs_url": "http://arxiv.org/abs/2408.14472v1",
  "venue": "RSS 2024",
  "venue_announced": "2026-06-26",
  "cover_image": "assets/img/covers/arxiv-2408-14472.jpg",
  "preview_pages": [
    "assets/img/covers/arxiv-2408-14472-p2.jpg",
    "assets/img/covers/arxiv-2408-14472-p3.jpg",
    "assets/img/covers/arxiv-2408-14472-p4.jpg"
  ],
  "channels": [
    "world-model",
    "locomotion",
    "loco-manip-wbc",
    "sim2real"
  ],
  "badges": [
    {
      "kind": "lab",
      "label": "⭐ RobotEra"
    },
    {
      "kind": "lab",
      "label": "⭐ 清华"
    },
    {
      "kind": "pin",
      "label": "📌 站长精选"
    },
    {
      "kind": "venue",
      "label": "🎓 RSS 2024"
    }
  ],
  "related_links": [
    {
      "source": "note",
      "source_name": "站长注解",
      "title": "Denoising World Model for Humanoid Locomotion｜复杂地形泛化",
      "url": "http://arxiv.org/abs/2408.14472v1"
    }
  ],
  "page_count": 14,
  "source_tags": [
    "manual_pin"
  ],
  "score": 85,
  "score_breakdown": [
    {
      "id": "manual_pin",
      "label": "站长亲自精选",
      "points": 30,
      "hint": "在 config/manual_arxiv.yaml 手动加进来的，默认高质量"
    },
    {
      "id": "famous_lab",
      "label": "顶尖实验室出品",
      "points": 25,
      "hint": "命中 “RobotEra” 关键词"
    },
    {
      "id": "keyword_density",
      "label": "关键词命中密集",
      "points": 12,
      "hint": "频道关键词命中 6 个（world model、locomotion、humanoid loco、humanoid robot）"
    },
    {
      "id": "longer_paper",
      "label": "成型 paper (≥4 页)",
      "points": 3,
      "hint": "PDF 14 页"
    },
    {
      "id": "conf_venue",
      "label": "机器人顶会 / 顶刊出品",
      "points": 10,
      "hint": "被「RSS 2024」收录"
    },
    {
      "id": "cross_channel",
      "label": "跨多个方向",
      "points": 5,
      "hint": "同时命中 4 个频道"
    }
  ],
  "judge": {},
  "institutions": [
    "RobotEra TECHNOLOGY CO., LTD.",
    "Tsinghua University",
    "Shanghai Qi Zhi Institute"
  ],
  "method_tags": [
    "Denoising World Model Learning",
    "reinforcement learning",
    "sim-to-real"
  ],
  "platform": [],
  "sim_stack": [],
  "method_family": "",
  "real_robot": "yes",
  "training_summary": "",
  "demo_videos": [],
  "github": {},
  "note": "---\ntags:\n  - 论文/方法\n  - Domain/Robotics\n  - Task/EmbodiedAI\nTitle: \"Advancing Humanoid Locomotion: Mastering Challenging Terrains with Denoising World Model Learning\"\nYear: \"2024\"\nURL: http://arxiv.org/abs/2408.14472v1\n---\n>[!abstract] 一句话总结：提出去噪世界模型学习（DWL），一种端到端强化学习框架，通过学习隐式动力学模型和去噪策略实现复杂地形人形机器人控制。\n\n\n# 一、动机\n\n> 现有基于模型控制或无模型强化学习的人形机器人只能应对简单地形，无法在雪地、斜坡、楼梯等复杂真实环境中稳定行走。\n\n\n# 二、方法\n\n> 提出去噪世界模型学习（DWL），一种端到端强化学习框架，通过学习隐式动力学模型和去噪策略实现复杂地形人形机器人控制。\n\n\n# 三、核心实验结果\n\n> 在真实世界中首次实现人形机器人零样本迁移至雪地、倾斜地面、上下楼梯和极端不平坦地形，所有环境使用同一网络，展现强鲁棒性和泛化能力。\n\n\n# 四、对我的启发\n\n> 零样本迁移能力表明学习到的世界模型具有高度通用性，但仿真到现实的差距可能限制在更动态环境中的表现，未来需结合更真实的仿真或在线适应机制。\n"
}