{
  "id": "arxiv-2605-07703",
  "source": "arxiv",
  "title": "Finite-Time Analysis of MCTS in Continuous POMDP Planning",
  "title_zh": "连续POMDP规划中MCTS的有限时间分析",
  "abstract": "This paper presents a finite-time analysis for Monte Carlo Tree Search (MCTS) in Partially Observable Markov Decision Processes (POMDPs), with probabilistic concentration bounds in both discrete and continuous observation spaces. While MCTS-style solvers such as POMCP achieve empirical success in many applications, rigorous finite-time guarantees remain an open problem due to the nonstationarity and the interdependencies induced by heuristic action selection (e.g., UCB). In the discrete setting, we address these challenges by extending the polynomial exploration bonus to UCB in POMDP setting, yielding polynomial concentration bounds for the empirical value estimation at the root node. For continuous observation spaces, we introduce an abstract partitioning framework and propose a finite-time bound on partitioning loss. Under mild conditions, we prove highprobability bound on value estimates in POMDPs with continuous observation space. Specifically, we propose Voro-POMCPOW, a variant of POMCPOW with f inite-time guarantees that adaptively partitions the continuous observation space using Voronoi cells. This approach maintains a finite branching factor while preserving the original observation generator. Empirical validation demonstrates that the proposed Voro-POMCPOW shows competitive performance while providing theoretical guarantees. Although our analysis focuses on continuous POMDPs, the techniques developed herein are also applicable to continuous MDPs, closing another gap on the MDP side.",
  "abstract_zh": "本文对部分可观测马尔可夫决策过程（POMDP）中的蒙特卡洛树搜索（MCTS）进行了有限时间分析，在离散和连续观测空间下给出了概率浓度界。尽管POMCP等MCTS类求解器在许多应用中取得了经验成功，但由于启发式动作选择（如UCB）导致的非平稳性和相互依赖性，严格的有限时间保证仍然是一个开放问题。在离散设置中，我们通过将多项式探索奖励扩展到POMDP设置下的UCB，解决了这些挑战，得到了根节点经验价值估计的多项式浓度界。对于连续观测空间，我们引入了一个抽象划分框架，并提出了划分损失的有限时间界。在温和条件下，我们证明了具有连续观测空间的POMDP中价值估计的高概率界。具体来说，我们提出了Voro-POMCPOW，它是POMCPOW的一个变体，具有有限时间保证，使用Voronoi单元自适应地划分连续观测空间。该方法在保持原始观测生成器的同时维持有限分支因子。实验验证表明，所提出的Voro-POMCPOW在提供理论保证的同时表现出竞争性能。尽管我们的分析聚焦于连续POMDP，但本文开发的技术也适用于连续MDP，从而填补了MDP方面的另一个空白。",
  "tldr_zh": "首次给出连续POMDP中MCTS的有限时间理论保证，提出Voro-POMCPOW算法。",
  "cover_zh": "连续POMDP规划终于有理论保证｜Voro-POMCPOW让MCTS不再玄学",
  "authors": [
    {
      "name": "Da Kong",
      "affiliation": ""
    },
    {
      "name": "Vadim Indelman",
      "affiliation": ""
    }
  ],
  "primary_category": "cs.AI",
  "categories": [
    "cs.AI",
    "cs.RO"
  ],
  "published": "2026-05-08",
  "updated": "2026-05-08",
  "arxiv_id": "2605.07703",
  "pdf_url": "https://arxiv.org/pdf/2605.07703v1",
  "abs_url": "http://arxiv.org/abs/2605.07703v1",
  "cover_image": "assets/img/covers/arxiv-2605-07703.jpg",
  "preview_pages": [
    "assets/img/covers/arxiv-2605-07703-p2.jpg",
    "assets/img/covers/arxiv-2605-07703-p3.jpg",
    "assets/img/covers/arxiv-2605-07703-p4.jpg"
  ],
  "channels": [
    "perception"
  ],
  "badges": [],
  "related_links": [],
  "page_count": 17,
  "source_tags": [],
  "score": 8,
  "score_breakdown": [
    {
      "id": "keyword_density",
      "label": "关键词命中密集",
      "points": 3,
      "hint": "频道关键词命中 1 个（exploration）"
    },
    {
      "id": "longer_paper",
      "label": "正经长 paper (≥8 页)",
      "points": 5,
      "hint": "PDF 17 页"
    }
  ]
}