{
  "id": "arxiv-2605-07418",
  "source": "arxiv",
  "title": "Learning Image-Adaptive Scale Fields for Metric Depth Recovery",
  "title_zh": "学习图像自适应尺度场用于度量深度恢复",
  "abstract": "Monocular depth estimation (MDE) typically produces depth estimations that are defined up to an unknown scale or shift. When only sparse metric anchors are available, recovering accurate metric depth becomes challenging yet necessary for practical applications. We address this problem by formulating metric depth recovery as image-adaptive scale field modeling. Instead of directly correcting the depth, we reformulate the correction as a low-dimensional linear combination of image-adaptive basis maps. These maps are derived from semantic and geometric cues encoded in the MDE estimations and intermediate representations. The weights of basis maps are efficiently determined from sparse metric anchors via a least-squares problem. This formulation yields improved metric depth accuracy, strong robustness under extreme anchor sparsity, and an interpretable decomposition of spatial scale variations. Extensive experiments across multiple datasets and representative MDE models demonstrate the effectiveness and general applicability of our approach.",
  "abstract_zh": "单目深度估计（MDE）通常产生定义在未知尺度或偏移下的深度估计。当仅有稀疏度量锚点时，恢复准确的度量深度变得具有挑战性，但对实际应用至关重要。我们通过将度量深度恢复建模为图像自适应尺度场来解决这个问题。我们不直接修正深度，而是将修正重新表述为图像自适应基映射的低维线性组合。这些映射源自MDE估计和中间表示中编码的语义和几何线索。基映射的权重通过最小二乘问题从稀疏度量锚点中高效确定。这种公式提高了度量深度精度，在极端锚点稀疏性下具有强鲁棒性，并提供了空间尺度变化的可解释分解。在多个数据集和代表性MDE模型上的大量实验证明了我们方法的有效性和通用适用性。",
  "tldr_zh": "提出图像自适应尺度场，从稀疏锚点恢复度量深度，提升精度与鲁棒性。",
  "cover_zh": "单目深度估计不准？用图像自适应尺度场，稀疏锚点也能恢复精确度量深度！",
  "authors": [
    {
      "name": "Yuanyan Li",
      "affiliation": ""
    },
    {
      "name": "Matthias Althoff",
      "affiliation": ""
    }
  ],
  "primary_category": "cs.CV",
  "categories": [
    "cs.CV"
  ],
  "published": "2026-05-08",
  "updated": "2026-05-08",
  "arxiv_id": "2605.07418",
  "pdf_url": "https://arxiv.org/pdf/2605.07418v1",
  "abs_url": "http://arxiv.org/abs/2605.07418v1",
  "cover_image": "assets/img/covers/arxiv-2605-07418.jpg",
  "preview_pages": [
    "assets/img/covers/arxiv-2605-07418-p2.jpg",
    "assets/img/covers/arxiv-2605-07418-p3.jpg",
    "assets/img/covers/arxiv-2605-07418-p4.jpg"
  ],
  "channels": [
    "perception"
  ],
  "badges": [],
  "related_links": [],
  "page_count": 12,
  "source_tags": [],
  "score": 8,
  "score_breakdown": [
    {
      "id": "keyword_density",
      "label": "关键词命中密集",
      "points": 3,
      "hint": "频道关键词命中 1 个（depth estimation）"
    },
    {
      "id": "longer_paper",
      "label": "正经长 paper (≥8 页)",
      "points": 5,
      "hint": "PDF 12 页"
    }
  ]
}