{
  "id": "vid-youtube-zoMDadPQLKA",
  "source": "video_youtube",
  "title": "10m/s!! Unitree Breaks the World Record Again😊",
  "title_zh": "10m/s!! Unitree Breaks the World Record Again😊",
  "abstract": "With the physique of an ordinary person, running at a world champion’s speed!\nLeg length: 0.4+0.4=0.8m, body weight: approx. 62kg!\nH1: “Give me one more chance, give the world one more honor!”\n#unitree  #flyingman  #humanoidrobot  #embodiedai  #worldchampionship  #agi  #running  #sprint",
  "abstract_zh": "",
  "tldr_zh": "",
  "cover_zh": "",
  "authors": [],
  "primary_category": "video",
  "categories": [],
  "published": "2026-04-11",
  "updated": "",
  "arxiv_id": "",
  "pdf_url": "",
  "abs_url": "https://www.youtube.com/watch?v=zoMDadPQLKA",
  "cover_image": "",
  "preview_pages": [],
  "channels": [],
  "badges": [],
  "related_links": [],
  "page_count": 0,
  "source_tags": [],
  "score": 40,
  "score_breakdown": [
    {
      "id": "famous_lab",
      "label": "顶尖实验室出品",
      "points": 25,
      "hint": "命中 “Unitree” 关键词"
    },
    {
      "id": "from_media",
      "label": "公众号 / 社区精选",
      "points": 15,
      "hint": "来自 YouTube 视频"
    }
  ],
  "judge": {},
  "institutions": [
    "Unitree Robotics"
  ],
  "method_tags": [],
  "platform": [],
  "sim_stack": [],
  "method_family": "",
  "real_robot": "",
  "training_summary": "",
  "demo_videos": [
    {
      "kind": "youtube",
      "url": "https://www.youtube.com/watch?v=zoMDadPQLKA",
      "embed_url": "https://www.youtube.com/embed/zoMDadPQLKA",
      "title": "10m/s!! Unitree Breaks the World Record Again😊",
      "source": "channel"
    }
  ]
}